pymink/__init__.py
pymink/_exceptions.py
pymink/cleaner.py
pymink/cli.py
pymink/ngram.py
pymink/Test/__init__.py
pymink/Test/test.py
pymink-0.1.4.dist-info/LICENSE.txt
pymink-0.1.4.dist-info/METADATA
pymink-0.1.4.dist-info/WHEEL
pymink-0.1.4.dist-info/entry_points.txt
pymink-0.1.4.dist-info/top_level.txt
pymink-0.1.4.dist-info/RECORD
